{
    "ships": {
        "arknights_w": {
            "azurlane_st. louis":  [{
                "nsfw": 0,
                "linkType": "gelbooru",
                "link": "https://gelbooru.com/index.php?page=post&s=view&id=5378769",
                "imageId": "cb/3d/cb3d12563ee920eabacf0c3be0dae01a.jpg",
                "comment": "Image no longer available on Pixiv"
            }]
        },
        "azurlane_prinz eugen": {
            "kancolle_prinz eugen":  [{
                "nsfw": 0,
                "linkType": "pixiv",
                "link": "https://www.pixiv.net/en/artworks/65619644",
                "artist": "只有弱者才睡觉"
            }, {
                "nsfw": 0,
                "linkType": "pixiv",
                "link": "https://www.pixiv.net/en/artworks/65706374",
                "artist": "リン☆ユウ＠新刊通販委託中"
            }]
        },
        "kancolle_haruna": {
            "touhou_flandre scarlet":  [{
                "nsfw": 0,
                "linkType": "gelbooru",
                "link": "https://gelbooru.com/index.php?page=post&s=view&id=2272246",
                "imageId": "2a/3f/sample_2a3fe8b2ba697192628efcc6a781a31e.jpg",
                "comment": "Image no longer available on Pixiv"
            }]
        }
    }
}