{
    "ships": {
        "arknights_hoshiguma": {
            "fate_shuten dōji":  [{
                "nsfw": 0,
                "linkType": "pixiv",
                "link": "https://www.pixiv.net/en/artworks/75979968",
                "artist": "ルルちゃん"
            }]
        },
        "arknights_w": {
            "azurlane_st. louis":  [{
                "nsfw": 0,
                "linkType": "gelbooru",
                "link": "https://gelbooru.com/index.php?page=post&s=view&id=5378769",
                "imageId": "https://img2.gelbooru.com/images/cb/3d/cb3d12563ee920eabacf0c3be0dae01a.jpg",
                "comment": "Image no longer available on Pixiv"
            }]
        },
        "azurlane_prinz eugen": {
            "kancolle_prinz eugen":  [{
                "nsfw": 0,
                "linkType": "pixiv",
                "link": "https://www.pixiv.net/en/artworks/65619644",
                "artist": "只有弱者才睡觉"
            }, {
                "nsfw": 0,
                "linkType": "pixiv",
                "link": "https://www.pixiv.net/en/artworks/65706374",
                "artist": "リン☆ユウ＠新刊通販委託中"
            }]
        },
        "fate_scáthach": {
            "fireemblem_tharja":  [{
                "nsfw": 0,
                "linkType": "sankaku",
                "link": "https://beta.sankakucomplex.com/post/show/7552773?tags=fire_emblem%20fate_%28series%29",
                "imageId": "https://cs.sankakucomplex.com/data/00/2a/002a2a2caa1dedb9aa607a5efd57cb8b.png?e=1601039331&m=RszLqihmR_HMfXJ0LRuIyw",
                "comment": "Source not available"
            }]
        },
        "kancolle_haruna": {
            "touhou_flandre scarlet":  [{
                "nsfw": 0,
                "linkType": "gelbooru",
                "link": "https://gelbooru.com/index.php?page=post&s=view&id=2272246",
                "imageId": "https://img2.gelbooru.com/images/2a/3f/2a3fe8b2ba697192628efcc6a781a31e.jpg",
                "comment": "Image no longer available on Pixiv"
            }]
        },
        "touhou_reimu hakurei": {
            "vocaloid_miku hatsune":  [{
                "nsfw": 0,
                "linkType": "gelbooru",
                "link": "https://gelbooru.com/index.php?page=post&s=view&id=580377",
                "imageId": "https://img2.gelbooru.com/images/d3/ad/d3adc9f9abf522b7b845ae546792020d.jpg",
                "comment": "Image no longer available on Pixiv"
            }]
        }
    }
}